gtimeit/__init__.py
gtimeit/benchmark.py
gtimeit/perf_tracker.py
gtimeit-0.0.5.dist-info/LICENSE
gtimeit-0.0.5.dist-info/METADATA
gtimeit-0.0.5.dist-info/WHEEL
gtimeit-0.0.5.dist-info/top_level.txt
gtimeit-0.0.5.dist-info/RECORD
