Metadata-Version: 2.1
Name: gtimeit
Version: 0.0.5
Summary: Timer, benchmark and ressource usage tracker. A tool for python functions. Time and compare your functions inside or outside a program.
Home-page: https://github.com/Chthi/gtimeit
Author: Thibault Charmet
Author-email: 
License: UNKNOWN
Keywords: time benchmark track plot compare
Platform: UNKNOWN
Classifier: Programming Language :: Python :: 3
Classifier: License :: OSI Approved :: MIT License
Requires-Python: >=3.6
